vsmuxtools/__init__.py
vsmuxtools/_version.py
vsmuxtools/py.typed
vsmuxtools/extension/__init__.py
vsmuxtools/extension/audio.py
vsmuxtools/extension/chapters.py
vsmuxtools/extension/sub.py
vsmuxtools/utils/__init__.py
vsmuxtools/utils/audio.py
vsmuxtools/utils/source.py
vsmuxtools/video/__init__.py
vsmuxtools/video/clip_metadata.py
vsmuxtools/video/resumable.py
vsmuxtools/video/settings.py
vsmuxtools/video/testing.py
vsmuxtools/video/encoders/__init__.py
vsmuxtools/video/encoders/base.py
vsmuxtools/video/encoders/ffmpeg.py
vsmuxtools/video/encoders/intermediary.py
vsmuxtools/video/encoders/standalone.py
vsmuxtools/video/encoders/types.py
vsmuxtools-0.4.2.dist-info/METADATA
vsmuxtools-0.4.2.dist-info/WHEEL
vsmuxtools-0.4.2.dist-info/licenses/LICENSE
vsmuxtools-0.4.2.dist-info/RECORD
