Metadata-Version: 2.4
Name: vsmuxtools
Version: 0.4.2
Summary: The extension to muxtools with vapoursynth and encoding stuff
Project-URL: Source Code, https://github.com/Vodes/vs-muxtools
Author-email: Vodes <vodes.imp@gmail.com>
License-Expression: MPL-2.0
License-File: LICENSE
Classifier: Intended Audience :: Developers
Classifier: Intended Audience :: End Users/Desktop
Classifier: License :: OSI Approved :: Mozilla Public License 2.0 (MPL 2.0)
Classifier: Natural Language :: English
Classifier: Operating System :: OS Independent
Classifier: Programming Language :: Python :: 3.11
Classifier: Topic :: Multimedia :: Video
Classifier: Topic :: Multimedia :: Video :: Conversion
Classifier: Topic :: Multimedia :: Video :: Display
Classifier: Typing :: Typed
Requires-Python: >=3.11
Requires-Dist: muxtools>=0.4.1
Requires-Dist: numpy>=1.24.3
Requires-Dist: vapoursynth>=67
Requires-Dist: vsjetpack>=0.7.0
